dagster_pipes/__init__.py
dagster_pipes/py.typed
dagster_pipes/version.py
dagster_pipes-1.12.13.dist-info/licenses/LICENSE
dagster_pipes-1.12.13.dist-info/METADATA
dagster_pipes-1.12.13.dist-info/WHEEL
dagster_pipes-1.12.13.dist-info/top_level.txt
dagster_pipes-1.12.13.dist-info/RECORD
