Metadata-Version: 2.4
Name: dagster-pipes
Version: 1.12.13
Summary: Toolkit for Dagster integrations with transform logic outside of Dagster
Home-page: https://github.com/dagster-io/dagster/tree/master/python_modules/dagster-pipes
Author: Dagster Labs
Author-email: hello@dagsterlabs.com
License: Apache-2.0
Classifier: Programming Language :: Python :: 3.10
Classifier: Programming Language :: Python :: 3.11
Classifier: Programming Language :: Python :: 3.12
Classifier: Programming Language :: Python :: 3.13
Classifier: Programming Language :: Python :: 3.14
Classifier: License :: OSI Approved :: Apache Software License
Classifier: Operating System :: OS Independent
Requires-Python: >=3.10,<3.15
License-File: LICENSE
Provides-Extra: stubs
Requires-Dist: google-cloud-storage; extra == "stubs"
Dynamic: author
Dynamic: author-email
Dynamic: classifier
Dynamic: description
Dynamic: home-page
Dynamic: license
Dynamic: license-file
Dynamic: provides-extra
Dynamic: requires-python
Dynamic: summary
